[
    {
        "type": 0,
        "label": "13",
        "labels": "Default",
        "marked": false,
        "pts": [
            {
                "x": 575.510360314382,
                "y": 1347.3371440236806
            },
            {
                "x": 601.8367867714607,
                "y": 198.84678983362224
            }
        ]
    },
    {
        "type": 0,
        "label": "12",
        "labels": "Default",
        "marked": false,
        "pts": [
            {
                "x": 881.5550678779218,
                "y": 1363.791160559355
            },
            {
                "x": 911.1722976421354,
                "y": 425.91221802592617
            }
        ]
    }
]