[
    {
        "type": 0,
        "label": "16",
        "state": 0,
        "marked": false,
        "labels": "Dentes",
        "dente": -1,
        "pts": [
            {
                "x": 566.3305417518709,
                "y": 1053.5215141181486
            },
            {
                "x": 520.4131292252088,
                "y": 111.73565519413951
            }
        ]
    },
    {
        "type": 0,
        "label": "15",
        "state": 0,
        "marked": false,
        "labels": "Dentes",
        "dente": -1,
        "pts": [
            {
                "x": 944.172986517894,
                "y": 1134.6728255229996
            },
            {
                "x": 859.8176541690613,
                "y": 169.2431603484645
            }
        ]
    },
    {
        "type": 0,
        "label": "14",
        "state": 0,
        "marked": false,
        "labels": "Dentes",
        "dente": -1,
        "pts": [
            {
                "x": 1218.441139023999,
                "y": 1141.3847823216267
            },
            {
                "x": 1100.2221077713682,
                "y": 203.1068592522633
            }
        ]
    },
    {
        "type": 0,
        "label": "17",
        "state": 0,
        "marked": false,
        "labels": "Dentes",
        "dente": -1,
        "pts": [
            {
                "x": 104.55823561909733,
                "y": 954.4237946106483
            },
            {
                "x": 150.81334912204264,
                "y": 138.65179283143127
            }
        ]
    },
    {
        "type": 0,
        "label": "13",
        "state": 0,
        "marked": false,
        "labels": "Dentes",
        "dente": -1,
        "pts": [
            {
                "x": 1525.8517232550528,
                "y": 1152.0592795777782
            },
            {
                "x": 1284.0636299442015,
                "y": 105.01171028383453
            }
        ]
    }
]