[
    {
        "type": 0,
        "label": "13",
        "state": 0,
        "marked": false,
        "labels": "Dentes",
        "dente": -1,
        "pts": [
            {
                "x": 704.202289307534,
                "y": 597.8258350964538
            },
            {
                "x": 691.4644331547366,
                "y": 159.2623088742284
            }
        ]
    },
    {
        "type": 0,
        "label": "14",
        "state": 0,
        "marked": false,
        "labels": "Dentes",
        "dente": -1,
        "pts": [
            {
                "x": 547.8093688135884,
                "y": 617.3940436917234
            },
            {
                "x": 540.1179028585411,
                "y": 230.61271791038158
            }
        ]
    },
    {
        "type": 0,
        "label": "15",
        "state": 0,
        "marked": false,
        "labels": "Dentes",
        "dente": -1,
        "pts": [
            {
                "x": 400.6167176658731,
                "y": 610.5636912492508
            },
            {
                "x": 380.9867738510309,
                "y": 303.254267288487
            }
        ]
    },
    {
        "type": 0,
        "label": "16",
        "state": 0,
        "marked": false,
        "labels": "Dentes",
        "dente": -1,
        "pts": [
            {
                "x": 243.6702999034019,
                "y": 606.9329716864172
            },
            {
                "x": 211.67185139938493,
                "y": 173.23063000322188
            }
        ]
    },
    {
        "type": 0,
        "label": "17",
        "state": 0,
        "marked": false,
        "labels": "Dentes",
        "dente": -1,
        "pts": [
            {
                "x": 99.15412204967846,
                "y": 589.3339309945892
            },
            {
                "x": 50.3256734639568,
                "y": 166.86170192682343
            }
        ]
    }
]