[
    {
        "type": 0,
        "label": "37",
        "state": 0,
        "marked": false,
        "labels": "Dentes",
        "dente": -1,
        "pts": [
            {
                "x": 1497.8872328754767,
                "y": 294.04987226112826
            },
            {
                "x": 1453.9300329115447,
                "y": 1023.7393916624079
            }
        ]
    },
    {
        "type": 0,
        "label": "36",
        "state": 0,
        "marked": false,
        "labels": "Dentes",
        "dente": -1,
        "pts": [
            {
                "x": 1005.5665932794326,
                "y": 272.071272279162
            },
            {
                "x": 1080.2938332181168,
                "y": 1111.6537915902732
            }
        ]
    },
    {
        "type": 0,
        "label": "35",
        "state": 0,
        "marked": false,
        "labels": "Dentes",
        "dente": -1,
        "pts": [
            {
                "x": 634.1816777504791,
                "y": 199.1679231747398
            },
            {
                "x": 689.0747535391184,
                "y": 975.3864717020821
            }
        ]
    },
    {
        "type": 0,
        "label": "34",
        "state": 0,
        "marked": false,
        "labels": "Dentes",
        "dente": -1,
        "pts": [
            {
                "x": 394.6683621133232,
                "y": 126.47827073542248
            },
            {
                "x": 314.2632221876153,
                "y": 996.830830021286
            }
        ]
    }
]