[
    {
        "type": 1,
        "label": "Perda \u00f3ssea",
        "state": 0,
        "marked": false,
        "labels": "Default",
        "dente": -1,
        "pts": [
            {
                "x": 994.0088848753309,
                "y": 201.68517826639757
            },
            {
                "x": 1311.8465814404328,
                "y": 1099.987024896403
            }
        ]
    },
    {
        "type": 1,
        "label": "Perda \u00f3ssea",
        "state": 0,
        "marked": false,
        "labels": "Default",
        "dente": -1,
        "pts": [
            {
                "x": 1338.7061050938212,
                "y": 165.87248006187906
            },
            {
                "x": 1652.0672143833601,
                "y": 1067.1587182089281
            }
        ]
    }
]