[
    {
        "type": 6,
        "label": "18",
        "state": 0,
        "marked": false,
        "labels": "Segmentacao",
        "dente": -1,
        "pts": [
            {
                "x": 345.23659390388,
                "y": 673.3064776405204
            },
            {
                "x": 345.23659390388,
                "y": 576.6107368941484
            },
            {
                "x": 335.87894157358596,
                "y": 453.40164787861
            },
            {
                "x": 320.2828543564292,
                "y": 342.66942863679685
            },
            {
                "x": 335.87894157358596,
                "y": 309.91764548076765
            },
            {
                "x": 377.9883770599092,
                "y": 302.11960187218926
            },
            {
                "x": 373.3095508947622,
                "y": 236.61603556013085
            },
            {
                "x": 367.0711160078995,
                "y": 182.0297303000822
            },
            {
                "x": 399.8228991639287,
                "y": 188.2681651869449
            },
            {
                "x": 445.0515520936833,
                "y": 233.49681811669953
            },
            {
                "x": 482.48216141485955,
                "y": 300.5599931504736
            },
            {
                "x": 530.8300317880455,
                "y": 323.95412397620873
            },
            {
                "x": 586.9759457698099,
                "y": 353.5866896888066
            },
            {
                "x": 640.0026423081429,
                "y": 422.20947344429635
            },
            {
                "x": 674.3140341858877,
                "y": 495.51108336493314
            },
            {
                "x": 682.1120777944661,
                "y": 587.527997946158
            },
            {
                "x": 677.4332516293191,
                "y": 673.3064776405203
            },
            {
                "x": 682.1120777944661,
                "y": 762.2041747783138
            },
            {
                "x": 710.1850347853476,
                "y": 843.3038283075289
            },
            {
                "x": 733.5791656110828,
                "y": 905.6881771761559
            },
            {
                "x": 730.4599481676514,
                "y": 961.8340911579203
            },
            {
                "x": 696.1485562899065,
                "y": 1011.7415702528219
            },
            {
                "x": 650.9199033601519,
                "y": 1036.6953098002728
            },
            {
                "x": 619.7277289258384,
                "y": 1032.016483635125
            },
            {
                "x": 593.2143806566719,
                "y": 1019.5396138613996
            },
            {
                "x": 571.3798585526524,
                "y": 1013.3011789745369
            },
            {
                "x": 547.9857277269173,
                "y": 1000.8243092008115
            },
            {
                "x": 521.4723794577508,
                "y": 1008.6223528093899
            },
            {
                "x": 484.04177013657454,
                "y": 1011.7415702528212
            },
            {
                "x": 448.170769537114,
                "y": 997.7050917573802
            },
            {
                "x": 401.3825078856437,
                "y": 968.0725260447823
            },
            {
                "x": 363.95189856446746,
                "y": 966.5129173230666
            },
            {
                "x": 326.5212892432912,
                "y": 950.9168301059099
            },
            {
                "x": 298.44833225240905,
                "y": 905.6881771761552
            },
            {
                "x": 296.88872353069337,
                "y": 840.1846108640968
            },
            {
                "x": 320.2828543564285,
                "y": 773.1214358303228
            },
            {
                "x": 332.7597241301539,
                "y": 746.6080875611563
            },
            {
                "x": 342.117376460448,
                "y": 707.6178695182643
            },
            {
                "x": 345.23659390387934,
                "y": 656.150781701647
            }
        ]
    },
    {
        "type": 6,
        "label": "17",
        "state": 0,
        "marked": false,
        "labels": "Segmentacao",
        "dente": -1,
        "pts": [
            {
                "x": 654.0391208035833,
                "y": 370.74238562767977
            },
            {
                "x": 664.956381855593,
                "y": 314.5964716459154
            },
            {
                "x": 682.1120777944654,
                "y": 241.29486172527862
            },
            {
                "x": 677.4332516293184,
                "y": 182.02973030008295
            },
            {
                "x": 700.8273824550536,
                "y": 158.6355994743482
            },
            {
                "x": 746.0560353848082,
                "y": 175.79129541322064
            },
            {
                "x": 783.4866447059844,
                "y": 213.22190473439687
            },
            {
                "x": 817.7980365837293,
                "y": 277.1658623247396
            },
            {
                "x": 839.6325586877488,
                "y": 345.78864608022934
            },
            {
                "x": 866.1459069569153,
                "y": 420.6498647225818
            },
            {
                "x": 892.6592552260818,
                "y": 511.10717058209104
            },
            {
                "x": 911.3745598866699,
                "y": 551.6569973466986
            },
            {
                "x": 923.8514296603953,
                "y": 503.30912697351266
            },
            {
                "x": 934.768690712405,
                "y": 436.2459519397386
            },
            {
                "x": 917.6129947735326,
                "y": 344.22903735851366
            },
            {
                "x": 934.768690712405,
                "y": 306.79842803733743
            },
            {
                "x": 975.3185174770126,
                "y": 302.1196018721904
            },
            {
                "x": 1012.7491267981889,
                "y": 334.8713850282196
            },
            {
                "x": 1043.9413012325024,
                "y": 403.49416878370937
            },
            {
                "x": 1079.812301831963,
                "y": 487.7130397563559
            },
            {
                "x": 1090.7295628839727,
                "y": 539.1801275729732
            },
            {
                "x": 1082.9315192753943,
                "y": 634.3162595976295
            },
            {
                "x": 1098.527606492551,
                "y": 701.3794346314036
            },
            {
                "x": 1142.19665070059,
                "y": 804.3136102646382
            },
            {
                "x": 1167.1503902480408,
                "y": 851.1018719161085
            },
            {
                "x": 1173.3888251349035,
                "y": 905.6881771761572
            },
            {
                "x": 1160.9119553611781,
                "y": 954.0360475493432
            },
            {
                "x": 1140.6370419788743,
                "y": 988.347439427088
            },
            {
                "x": 1103.206432657698,
                "y": 1011.7415702528232
            },
            {
                "x": 1053.2989535627955,
                "y": 1007.0627440876743
            },
            {
                "x": 1018.9875616850507,
                "y": 996.1454830356646
            },
            {
                "x": 986.2357785290216,
                "y": 983.6686132619392
            },
            {
                "x": 969.0800825901491,
                "y": 997.7050917573803
            },
            {
                "x": 936.3282994341199,
                "y": 1019.5396138613997
            },
            {
                "x": 895.7784726695123,
                "y": 1030.4568749134094
            },
            {
                "x": 841.1921674094637,
                "y": 1016.4203964179683
            },
            {
                "x": 795.963514479709,
                "y": 994.5858743139488
            },
            {
                "x": 761.6521226019642,
                "y": 997.7050917573802
            },
            {
                "x": 722.6619045590722,
                "y": 983.6686132619391
            },
            {
                "x": 693.0293388464751,
                "y": 935.3207428887532
            },
            {
                "x": 672.7544254641713,
                "y": 863.5787416898321
            },
            {
                "x": 674.314034185887,
                "y": 794.9559579343423
            },
            {
                "x": 685.2312952378967,
                "y": 738.810043952578
            },
            {
                "x": 678.992860351034,
                "y": 679.5449125273823
            },
            {
                "x": 674.314034185887,
                "y": 598.4452589981671
            },
            {
                "x": 661.8371644121615,
                "y": 503.30912697351084
            },
            {
                "x": 654.0391208035832,
                "y": 440.9247781048838
            },
            {
                "x": 652.4795120818675,
                "y": 386.3384728448351
            },
            {
                "x": 655.5987295252988,
                "y": 361.3847332973843
            }
        ]
    },
    {
        "type": 6,
        "label": "16",
        "state": 0,
        "marked": false,
        "labels": "Segmentacao",
        "dente": -1,
        "pts": [
            {
                "x": 1017.4279529633351,
                "y": 284.9639059333178
            },
            {
                "x": 1012.7491267981881,
                "y": 192.94699135209288
            },
            {
                "x": 1020.5471704067664,
                "y": 130.56264248346588
            },
            {
                "x": 1045.5009099542171,
                "y": 94.69164188400535
            },
            {
                "x": 1078.2526931102464,
                "y": 83.77438083199561
            },
            {
                "x": 1125.0409547617166,
                "y": 113.40694654459347
            },
            {
                "x": 1170.2696076914713,
                "y": 166.43364308292638
            },
            {
                "x": 1192.1041297954907,
                "y": 219.46033962125938
            },
            {
                "x": 1223.2963042298043,
                "y": 277.16586232473935
            },
            {
                "x": 1256.0480873858335,
                "y": 339.5502111933664
            },
            {
                "x": 1274.7633920464216,
                "y": 406.6133862271405
            },
            {
                "x": 1298.1575228721567,
                "y": 461.19969148718917
            },
            {
                "x": 1324.6708711413232,
                "y": 492.3918659215027
            },
            {
                "x": 1344.945784523627,
                "y": 484.5938223129243
            },
            {
                "x": 1351.1842194104897,
                "y": 401.93456006199347
            },
            {
                "x": 1340.26695835848,
                "y": 331.752167584788
            },
            {
                "x": 1329.3496973064703,
                "y": 256.89094894243556
            },
            {
                "x": 1338.7073496367643,
                "y": 208.54307856924962
            },
            {
                "x": 1369.8995240710778,
                "y": 188.26816518694582
            },
            {
                "x": 1410.4493508356854,
                "y": 206.98346984753394
            },
            {
                "x": 1450.999177600293,
                "y": 281.8446884898864
            },
            {
                "x": 1483.7509607563222,
                "y": 353.5866896888075
            },
            {
                "x": 1508.704700303773,
                "y": 428.44790833115997
            },
            {
                "x": 1524.3007875209298,
                "y": 487.71303975635567
            },
            {
                "x": 1527.4200049643612,
                "y": 528.2628665209633
            },
            {
                "x": 1525.8603962426455,
                "y": 615.6009549370411
            },
            {
                "x": 1532.0988311295082,
                "y": 677.9853038056682
            },
            {
                "x": 1553.9333532335277,
                "y": 734.1312177874325
            },
            {
                "x": 1574.2082666158315,
                "y": 777.8002619954715
            },
            {
                "x": 1586.6851363895569,
                "y": 818.3500887600791
            },
            {
                "x": 1588.2447451112726,
                "y": 860.4595242464023
            },
            {
                "x": 1576.0797970818908,
                "y": 900.5726605689296
            },
            {
                "x": 1546.1353096249493,
                "y": 943.1187864973332
            },
            {
                "x": 1508.704700303773,
                "y": 950.9168301059116
            },
            {
                "x": 1460.356829930587,
                "y": 943.1187864973332
            },
            {
                "x": 1419.8070031659795,
                "y": 930.6419167236078
            },
            {
                "x": 1401.0916985053914,
                "y": 960.2744824362056
            },
            {
                "x": 1363.6610891842151,
                "y": 983.6686132619408
            },
            {
                "x": 1323.1112624196076,
                "y": 997.7050917573819
            },
            {
                "x": 1268.5249571595589,
                "y": 980.5493958185094
            },
            {
                "x": 1220.177086786373,
                "y": 929.0823080018921
            },
            {
                "x": 1174.9484338566183,
                "y": 933.7611341670391
            },
            {
                "x": 1143.7562594223048,
                "y": 933.7611341670391
            },
            {
                "x": 1115.6833024314226,
                "y": 911.9266120630197
            },
            {
                "x": 1087.6103454405404,
                "y": 849.5422631943926
            },
            {
                "x": 1076.6930843885307,
                "y": 785.5983056040499
            },
            {
                "x": 1073.5738669450993,
                "y": 727.8927829005698
            },
            {
                "x": 1082.9315192753934,
                "y": 657.7103904233644
            },
            {
                "x": 1090.7295628839718,
                "y": 581.2895630592963
            },
            {
                "x": 1087.6103454405404,
                "y": 511.1071705820908
            },
            {
                "x": 1061.096997171374,
                "y": 439.3651693831697
            },
            {
                "x": 1040.8220837890701,
                "y": 376.98082051454236
            },
            {
                "x": 1023.6663878501977,
                "y": 320.834906532778
            },
            {
                "x": 1015.8683442416193,
                "y": 258.45055766415095
            }
        ]
    }
]