[
    {
        "type": 6,
        "label": "37",
        "state": 0,
        "marked": false,
        "labels": "Segmentacao",
        "dente": -1,
        "pts": [
            {
                "x": 1152.7874989876889,
                "y": 619.3940901908398
            },
            {
                "x": 1096.2141569067517,
                "y": 515.5547584776097
            },
            {
                "x": 1057.4756901722315,
                "y": 436.5282863391888
            },
            {
                "x": 1034.2326101315193,
                "y": 365.249507547672
            },
            {
                "x": 1038.8812261396617,
                "y": 307.91657678058243
            },
            {
                "x": 1063.6738448497547,
                "y": 259.88087802977736
            },
            {
                "x": 1076.0701542048018,
                "y": 242.83595266659012
            },
            {
                "x": 1096.2141569067524,
                "y": 216.49379528711637
            },
            {
                "x": 1156.6461650126037,
                "y": 179.3048672219774
            },
            {
                "x": 1215.5286344490744,
                "y": 170.00763520569257
            },
            {
                "x": 1269.7624878774027,
                "y": 187.05256056888143
            },
            {
                "x": 1331.7440346526334,
                "y": 191.7011765770239
            },
            {
                "x": 1392.176042758485,
                "y": 200.99840859330874
            },
            {
                "x": 1441.7612801786709,
                "y": 235.08825931968644
            },
            {
                "x": 1471.2025148969062,
                "y": 276.9258033929681
            },
            {
                "x": 1486.6979015907143,
                "y": 329.6101181519155
            },
            {
                "x": 1489.796978929476,
                "y": 371.4476622251972
            },
            {
                "x": 1495.9951336069973,
                "y": 410.18612895971626
            },
            {
                "x": 1497.5446722763782,
                "y": 479.91536908185196
            },
            {
                "x": 1511.4905203008054,
                "y": 582.1849212609848
            },
            {
                "x": 1534.7336003415176,
                "y": 672.0581640850712
            },
            {
                "x": 1554.877603043468,
                "y": 734.0397108603036
            },
            {
                "x": 1556.4271417128489,
                "y": 800.6698736436783
            },
            {
                "x": 1556.4271417128489,
                "y": 868.8495750964337
            },
            {
                "x": 1557.9766803822297,
                "y": 937.0292765491893
            },
            {
                "x": 1557.9766803822297,
                "y": 992.8126686468984
            },
            {
                "x": 1531.634523002756,
                "y": 1003.659439332564
            },
            {
                "x": 1472.7520535662852,
                "y": 975.7677432837095
            },
            {
                "x": 1424.7163548154801,
                "y": 971.119127275567
            },
            {
                "x": 1362.7348080402478,
                "y": 960.2723565899014
            },
            {
                "x": 1314.6991092894427,
                "y": 907.5880418309539
            },
            {
                "x": 1262.0147945304952,
                "y": 837.8588017088176
            },
            {
                "x": 1213.9790957796902,
                "y": 772.7781775948237
            },
            {
                "x": 1179.8892450533124,
                "y": 676.7067800932135
            },
            {
                "x": 1142.700316988173,
                "y": 600.779385293554
            }
        ]
    },
    {
        "type": 6,
        "label": "36",
        "state": 0,
        "marked": false,
        "labels": "Segmentacao",
        "dente": -1,
        "pts": [
            {
                "x": 1116.3581596087024,
                "y": 639.5178520280738
            },
            {
                "x": 1134.952623641272,
                "y": 704.5984761420674
            },
            {
                "x": 1155.0966263432226,
                "y": 763.480945578538
            },
            {
                "x": 1184.537861061458,
                "y": 833.2101857006743
            },
            {
                "x": 1210.8800184409317,
                "y": 902.9394258228107
            },
            {
                "x": 1212.4295571103125,
                "y": 957.1732792511388
            },
            {
                "x": 1175.2406290451731,
                "y": 966.4705112674236
            },
            {
                "x": 1116.3581596087024,
                "y": 927.7320445329034
            },
            {
                "x": 1057.4756901722317,
                "y": 885.8945004596216
            },
            {
                "x": 1010.9895300908076,
                "y": 834.7597243700549
            },
            {
                "x": 973.8006020256682,
                "y": 744.8864815459683
            },
            {
                "x": 927.3144419442449,
                "y": 664.310470738166
            },
            {
                "x": 883.9273592015822,
                "y": 582.1849212609832
            },
            {
                "x": 852.9365858139661,
                "y": 605.4280013016953
            },
            {
                "x": 842.0898151283004,
                "y": 667.4095480769276
            },
            {
                "x": 859.1347404914893,
                "y": 747.9855588847297
            },
            {
                "x": 879.2787431934398,
                "y": 820.8138763456275
            },
            {
                "x": 887.0264365403439,
                "y": 896.7412711452871
            },
            {
                "x": 874.6301271852974,
                "y": 940.1283538879497
            },
            {
                "x": 823.4953510957307,
                "y": 916.8852738472376
            },
            {
                "x": 783.8271611595821,
                "y": 858.0028044107671
            },
            {
                "x": 749.1174949654521,
                "y": 772.7781775948231
            },
            {
                "x": 716.5771829084551,
                "y": 676.7067800932131
            },
            {
                "x": 707.2799508921703,
                "y": 566.6895345671759
            },
            {
                "x": 685.586409520839,
                "y": 486.11352375937406
            },
            {
                "x": 663.8928681495076,
                "y": 414.8347449678572
            },
            {
                "x": 639.1002494394147,
                "y": 345.1055048457213
            },
            {
                "x": 622.0553240762258,
                "y": 253.6827233522544
            },
            {
                "x": 646.8479427863188,
                "y": 170.00763520569149
            },
            {
                "x": 684.0368708514582,
                "y": 123.52147512426738
            },
            {
                "x": 721.2257989165998,
                "y": 121.97193645488808
            },
            {
                "x": 749.1174949654541,
                "y": 117.3233204467457
            },
            {
                "x": 787.8559616999743,
                "y": 126.62055246303046
            },
            {
                "x": 835.8916604507785,
                "y": 135.91778447931532
            },
            {
                "x": 883.9273592015836,
                "y": 135.91778447931532
            },
            {
                "x": 949.0079833155772,
                "y": 129.71962980179208
            },
            {
                "x": 981.5482953725742,
                "y": 146.76455516498098
            },
            {
                "x": 1013.1588842279428,
                "y": 179.92468268973016
            },
            {
                "x": 1050.347812293082,
                "y": 196.65970031904286
            },
            {
                "x": 1072.9710768660418,
                "y": 225.79102730340205
            },
            {
                "x": 1074.5206155354208,
                "y": 275.3762647235871
            },
            {
                "x": 1063.6738448497551,
                "y": 326.5110408131536
            },
            {
                "x": 1057.475690172232,
                "y": 365.24950754767383
            },
            {
                "x": 1054.3766128334703,
                "y": 442.72644101671386
            },
            {
                "x": 1066.772922188517,
                "y": 514.0052198082294
            },
            {
                "x": 1107.8171024630758,
                "y": 615.5185971167042
            },
            {
                "x": 1120.5754956201022,
                "y": 656.4883995351324
            }
        ]
    },
    {
        "type": 6,
        "label": "35",
        "state": 0,
        "marked": false,
        "labels": "Segmentacao",
        "dente": -1,
        "pts": [
            {
                "x": 604.6344612594452,
                "y": 473.1717767927067
            },
            {
                "x": 602.7790630291314,
                "y": 548.7892638584902
            },
            {
                "x": 611.4564795776643,
                "y": 664.0749408604227
            },
            {
                "x": 626.3320508037203,
                "y": 766.9643085073086
            },
            {
                "x": 639.9679910942712,
                "y": 856.2177358636407
            },
            {
                "x": 644.9265148362899,
                "y": 918.1992826388735
            },
            {
                "x": 643.6868839007852,
                "y": 982.6600912851156
            },
            {
                "x": 632.5302054812431,
                "y": 1024.8075430922743
            },
            {
                "x": 597.8205392871128,
                "y": 1032.2453287053024
            },
            {
                "x": 564.3505040284869,
                "y": 993.8167697046579
            },
            {
                "x": 525.9219450278416,
                "y": 915.7200207678644
            },
            {
                "x": 492.4519097692187,
                "y": 816.5495459274895
            },
            {
                "x": 466.4196601236213,
                "y": 707.4620236030802
            },
            {
                "x": 447.8251960910518,
                "y": 558.7063113425236
            },
            {
                "x": 418.07405363894054,
                "y": 426.06580124352746
            },
            {
                "x": 395.7606967998571,
                "y": 333.0934810806798
            },
            {
                "x": 380.8851255738015,
                "y": 298.38381488655
            },
            {
                "x": 353.6132449926995,
                "y": 247.55894653085994
            },
            {
                "x": 343.6961975086624,
                "y": 186.8170306911328
            },
            {
                "x": 349.8943521861856,
                "y": 139.71105514195665
            },
            {
                "x": 379.64549463829684,
                "y": 107.48065081883612
            },
            {
                "x": 418.07405363894054,
                "y": 90.12581772177123
            },
            {
                "x": 480.0556004141723,
                "y": 67.81246088268779
            },
            {
                "x": 527.161575963349,
                "y": 75.2502464957156
            },
            {
                "x": 585.4242299320681,
                "y": 91.36544865727586
            },
            {
                "x": 616.4150033196851,
                "y": 112.43917456085467
            },
            {
                "x": 635.009467352255,
                "y": 152.107364497003
            },
            {
                "x": 642.4472529652832,
                "y": 204.1718637881977
            },
            {
                "x": 633.7698364167503,
                "y": 248.79857746636458
            },
            {
                "x": 616.4150033196847,
                "y": 293.42529114453146
            },
            {
                "x": 607.7375867711519,
                "y": 376.48056382334204
            },
            {
                "x": 606.4979558356454,
                "y": 421.107277501512
            },
            {
                "x": 604.0105976187514,
                "y": 483.0969206226273
            }
        ]
    },
    {
        "type": 6,
        "label": "34",
        "state": 0,
        "marked": false,
        "labels": "Segmentacao",
        "dente": -1,
        "pts": [
            {
                "x": 280.4750197979261,
                "y": 416.14875375949345
            },
            {
                "x": 266.8390795073751,
                "y": 488.0473480187623
            },
            {
                "x": 256.92203202333803,
                "y": 597.1348703431714
            },
            {
                "x": 260.64092482985194,
                "y": 693.8260833125335
            },
            {
                "x": 265.5994485718705,
                "y": 776.8813559913445
            },
            {
                "x": 279.2353888624215,
                "y": 873.5725689607065
            },
            {
                "x": 279.2353888624215,
                "y": 929.3559610584164
            },
            {
                "x": 249.48424641031022,
                "y": 964.0656272525468
            },
            {
                "x": 204.85753273214334,
                "y": 951.6693178974999
            },
            {
                "x": 165.189342795995,
                "y": 897.1255567352946
            },
            {
                "x": 144.1156168924162,
                "y": 815.3099149919877
            },
            {
                "x": 131.71930753736984,
                "y": 728.5357495066625
            },
            {
                "x": 113.12484350480031,
                "y": 592.1763466011521
            },
            {
                "x": 98.24927227874468,
                "y": 449.61878901811883
            },
            {
                "x": 80.89443918167979,
                "y": 333.0934810806831
            },
            {
                "x": 59.82071327810098,
                "y": 241.36079185334006
            },
            {
                "x": 43.70551111654061,
                "y": 162.02441198104302
            },
            {
                "x": 56.10182047158696,
                "y": 114.91843643186684
            },
            {
                "x": 80.89443918167969,
                "y": 87.64655585076481
            },
            {
                "x": 108.16631976278167,
                "y": 64.09356807617675
            },
            {
                "x": 130.47967660186512,
                "y": 50.45762778562573
            },
            {
                "x": 176.34602121553664,
                "y": 34.34242562406547
            },
            {
                "x": 224.69162770021742,
                "y": 43.01984217259792
            },
            {
                "x": 279.2353888624214,
                "y": 66.572829947186
            },
            {
                "x": 316.4243169275605,
                "y": 90.12581772177407
            },
            {
                "x": 335.0187809601301,
                "y": 139.71105514195952
            },
            {
                "x": 337.49804283113934,
                "y": 202.93223285269593
            },
            {
                "x": 318.9035787985698,
                "y": 254.99673214389063
            },
            {
                "x": 301.5487457015049,
                "y": 300.86307675756217
            },
            {
                "x": 287.9128054109539,
                "y": 376.48056382334494
            },
            {
                "x": 276.7561269914122,
                "y": 432.26395592105354
            }
        ]
    },
    {
        "type": 6,
        "label": "33",
        "state": 0,
        "marked": false,
        "labels": "Segmentacao",
        "dente": -1,
        "pts": [
            {
                "x": 87.40250159307907,
                "y": 521.2074755435114
            },
            {
                "x": 95.15019493998304,
                "y": 618.8284117145021
            },
            {
                "x": 113.74465897255257,
                "y": 714.8998092161119
            },
            {
                "x": 132.33912300512213,
                "y": 790.8272040157715
            },
            {
                "x": 141.63635502140696,
                "y": 863.6555214766694
            },
            {
                "x": 135.43820034388366,
                "y": 947.3306096232308
            },
            {
                "x": 110.64558163379098,
                "y": 987.6186150271311
            },
            {
                "x": 76.5557309074135,
                "y": 993.8167697046543
            },
            {
                "x": 33.16864816475126,
                "y": 961.2764576476574
            },
            {
                "x": 13.024645462800933,
                "y": 902.3939882111866
            },
            {
                "x": 5.2769521158969575,
                "y": 829.5656707502886
            },
            {
                "x": 5.2769521158969575,
                "y": 693.206267844778
            },
            {
                "x": 3.727413446516162,
                "y": 549.0991715923635
            },
            {
                "x": 3.727413446516162,
                "y": 375.5508406217139
            },
            {
                "x": 5.2769521158969575,
                "y": 259.3354404181539
            },
            {
                "x": 17.673261470943316,
                "y": 188.0566616266371
            },
            {
                "x": 39.36680284227444,
                "y": 135.37234686768986
            },
            {
                "x": 68.80803756050953,
                "y": 153.9668109002596
            },
            {
                "x": 84.30342425431748,
                "y": 205.1015869898259
            },
            {
                "x": 79.6548082461751,
                "y": 288.7766751363892
            },
            {
                "x": 73.45665356865192,
                "y": 367.80314727480993
            },
            {
                "x": 82.75388558493668,
                "y": 465.4240834458003
            },
            {
                "x": 88.95204026245986,
                "y": 541.3514782454594
            }
        ]
    }
]