[
    {
        "type": 6,
        "label": "16",
        "state": 0,
        "marked": false,
        "labels": "Segmentacao",
        "dente": -1,
        "pts": [
            {
                "x": 461.2529336939035,
                "y": 238.24844147022037
            },
            {
                "x": 452.1298784357227,
                "y": 278.4710672433879
            },
            {
                "x": 437.1003251777232,
                "y": 361.42674490273976
            },
            {
                "x": 437.2180546277226,
                "y": 412.6774815153887
            },
            {
                "x": 435.5323407016154,
                "y": 457.463316078553
            },
            {
                "x": 404.1635118533225,
                "y": 424.60694056178875
            },
            {
                "x": 354.8413699899462,
                "y": 392.25803206379203
            },
            {
                "x": 339.27888119772985,
                "y": 423.5163369020626
            },
            {
                "x": 353.9544069701988,
                "y": 505.75112099540206
            },
            {
                "x": 373.18745932656645,
                "y": 599.2429982234173
            },
            {
                "x": 404.2921599742206,
                "y": 718.1262417939553
            },
            {
                "x": 389.28540996003665,
                "y": 775.3287869315121
            },
            {
                "x": 378.9068588089192,
                "y": 832.4751453582073
            },
            {
                "x": 372.2675820250689,
                "y": 888.3329103965019
            },
            {
                "x": 379.4158490615654,
                "y": 936.8181471507199
            },
            {
                "x": 399.7237414865461,
                "y": 982.4081645918002
            },
            {
                "x": 412.94771666154304,
                "y": 1040.115044207405
            },
            {
                "x": 439.98568912648744,
                "y": 1086.9702716814083
            },
            {
                "x": 502.9510488356705,
                "y": 1128.332024800366
            },
            {
                "x": 533.1309053607793,
                "y": 1123.1085796193047
            },
            {
                "x": 558.0714277404531,
                "y": 1121.072618608717
            },
            {
                "x": 584.3210895024287,
                "y": 1104.4387971074125
            },
            {
                "x": 625.6203620155435,
                "y": 1123.3815840793236
            },
            {
                "x": 729.3468882235045,
                "y": 1156.0475650850701
            },
            {
                "x": 796.9741920688092,
                "y": 1078.7592178332934
            },
            {
                "x": 823.5420614366074,
                "y": 1008.7166531363707
            },
            {
                "x": 821.2564909966036,
                "y": 940.4408972329958
            },
            {
                "x": 801.7505111949181,
                "y": 888.0187066782457
            },
            {
                "x": 801.8047137720455,
                "y": 844.4789152263451
            },
            {
                "x": 772.651006789393,
                "y": 761.8392539261865
            },
            {
                "x": 729.3468882235047,
                "y": 699.5632641292636
            },
            {
                "x": 692.3226781794745,
                "y": 623.8948804593449
            },
            {
                "x": 647.228019268492,
                "y": 484.60504833525937
            },
            {
                "x": 616.0792376268757,
                "y": 367.2752471112686
            },
            {
                "x": 570.0595910345193,
                "y": 269.7862943466782
            },
            {
                "x": 533.0720785781839,
                "y": 212.9579334309429
            },
            {
                "x": 492.65132476493795,
                "y": 199.60426784433196
            },
            {
                "x": 470.556916176062,
                "y": 216.89119964587078
            },
            {
                "x": 458.9673632538996,
                "y": 247.78956585888824
            }
        ]
    },
    {
        "type": 6,
        "label": "17",
        "state": 0,
        "marked": false,
        "labels": "Segmentacao",
        "dente": -1,
        "pts": [
            {
                "x": 8.44148460931378,
                "y": 837.4815416713463
            },
            {
                "x": 10.926788577313795,
                "y": 741.7973389033466
            },
            {
                "x": 14.157683735713817,
                "y": 674.6941317673452
            },
            {
                "x": 35.77982825731392,
                "y": 629.9586603433459
            },
            {
                "x": 48.20634809731398,
                "y": 591.4364488393467
            },
            {
                "x": 48.20634809731398,
                "y": 535.5171095593467
            },
            {
                "x": 58.14756396931402,
                "y": 460.9579905193459
            },
            {
                "x": 78.02999571331415,
                "y": 397.58273933534366
            },
            {
                "x": 95.42712348931423,
                "y": 344.1487040233433
            },
            {
                "x": 101.64038340931428,
                "y": 270.83223696734274
            },
            {
                "x": 118.2919199949144,
                "y": 214.41583689374238
            },
            {
                "x": 128.97872705731444,
                "y": 165.2068183273421
            },
            {
                "x": 160.04502665731482,
                "y": 134.14051872734242
            },
            {
                "x": 225.90558180931512,
                "y": 151.5376465033427
            },
            {
                "x": 256.9718814093152,
                "y": 190.0598580073429
            },
            {
                "x": 278.0969651373154,
                "y": 249.70715323934343
            },
            {
                "x": 285.5528770413155,
                "y": 315.567708391344
            },
            {
                "x": 300.46470084931576,
                "y": 386.3988714793448
            },
            {
                "x": 320.347132593316,
                "y": 482.08307424734556
            },
            {
                "x": 331.5310004493161,
                "y": 556.6421932873457
            },
            {
                "x": 332.7736524333161,
                "y": 596.4070567753454
            },
            {
                "x": 317.86182862531587,
                "y": 673.4514797833456
            },
            {
                "x": 329.04569648131604,
                "y": 745.5252948553461
            },
            {
                "x": 345.20017227331624,
                "y": 802.6872861193464
            },
            {
                "x": 372.5385159213165,
                "y": 863.5772333353467
            },
            {
                "x": 392.42094766531665,
                "y": 920.7392245993464
            },
            {
                "x": 392.42094766531665,
                "y": 981.6291718153462
            },
            {
                "x": 375.0238198893164,
                "y": 1022.6366872873464
            },
            {
                "x": 346.44282425731626,
                "y": 1059.9162468073464
            },
            {
                "x": 321.58978457731604,
                "y": 1076.0707225993467
            },
            {
                "x": 293.0087889453158,
                "y": 1083.526634503347
            },
            {
                "x": 253.24392545731536,
                "y": 1072.3427666473463
            },
            {
                "x": 210.99375800131506,
                "y": 1053.7029868873456
            },
            {
                "x": 179.9274584013148,
                "y": 1037.548511095345
            },
            {
                "x": 158.80237467331463,
                "y": 1015.180775383345
            },
            {
                "x": 143.7931269497689,
                "y": 1012.5861180407552
            },
            {
                "x": 131.1200649561431,
                "y": 1024.3883295239912
            },
            {
                "x": 101.64038340931431,
                "y": 1035.0632071273478
            },
            {
                "x": 66.84612785731414,
                "y": 1036.305859111348
            },
            {
                "x": 29.566568337313953,
                "y": 1041.2764670473482
            },
            {
                "x": 19.625352465313906,
                "y": 1025.1219912553472
            },
            {
                "x": 9.684136593313848,
                "y": 980.3865198313476
            },
            {
                "x": 8.441484609313841,
                "y": 925.7098325353478
            },
            {
                "x": 8.441484609313841,
                "y": 828.7829777833477
            }
        ]
    },
    {
        "type": 6,
        "label": "15",
        "state": 0,
        "marked": false,
        "labels": "Segmentacao",
        "dente": -1,
        "pts": [
            {
                "x": 890.7800640582014,
                "y": 337.99310315540134
            },
            {
                "x": 921.8463636582017,
                "y": 416.2801781474019
            },
            {
                "x": 942.9714473862012,
                "y": 502.0231650434026
            },
            {
                "x": 962.8538791302011,
                "y": 590.2514559074028
            },
            {
                "x": 991.4348747622007,
                "y": 682.207702723403
            },
            {
                "x": 1016.2879144422004,
                "y": 771.6786455714027
            },
            {
                "x": 1038.6556501542009,
                "y": 844.9951126274026
            },
            {
                "x": 1043.626258090202,
                "y": 898.4291479394035
            },
            {
                "x": 1020.0158703942016,
                "y": 946.8925753154031
            },
            {
                "x": 997.6481346822021,
                "y": 997.841306659403
            },
            {
                "x": 960.3685751622022,
                "y": 1041.3341260994036
            },
            {
                "x": 920.6037116742021,
                "y": 1067.4298177634037
            },
            {
                "x": 883.3241521542026,
                "y": 1055.003297923403
            },
            {
                "x": 847.2872446182026,
                "y": 1017.723738403402
            },
            {
                "x": 833.6180727942029,
                "y": 977.9588749154022
            },
            {
                "x": 821.1915529542031,
                "y": 939.4366634114025
            },
            {
                "x": 816.2209450182032,
                "y": 897.1864959554026
            },
            {
                "x": 812.4929890662033,
                "y": 831.3259408034029
            },
            {
                "x": 806.2797291462035,
                "y": 765.4653856514032
            },
            {
                "x": 780.1840374822037,
                "y": 648.6560991554041
            },
            {
                "x": 765.2722136742013,
                "y": 554.2145483714025
            },
            {
                "x": 745.3897819302014,
                "y": 432.43465393940147
            },
            {
                "x": 716.8087862982022,
                "y": 324.3239313314007
            },
            {
                "x": 721.7793942342005,
                "y": 251.00746427540037
            },
            {
                "x": 747.8750858982,
                "y": 205.0293408673999
            },
            {
                "x": 797.5811652581998,
                "y": 197.57342896339978
            },
            {
                "x": 841.0739846981991,
                "y": 224.91177261140012
            },
            {
                "x": 865.927024378199,
                "y": 270.88989601940057
            },
            {
                "x": 880.8388481861988,
                "y": 311.897411491401
            },
            {
                "x": 895.72959661655,
                "y": 349.17697101140135
            }
        ]
    },
    {
        "type": 6,
        "label": "14",
        "state": 0,
        "marked": false,
        "labels": "Segmentacao",
        "dente": -1,
        "pts": [
            {
                "x": 1200.4433865242577,
                "y": 582.4766289685457
            },
            {
                "x": 1214.0571726252604,
                "y": 656.7336440649219
            },
            {
                "x": 1233.859043317628,
                "y": 740.8915945074821
            },
            {
                "x": 1242.5223617455392,
                "y": 796.5843558297644
            },
            {
                "x": 1261.0866155196336,
                "y": 834.9504802962256
            },
            {
                "x": 1282.126103130274,
                "y": 884.4551570271431
            },
            {
                "x": 1295.7398892312765,
                "y": 925.2965153301496
            },
            {
                "x": 1314.3041430053718,
                "y": 964.9002567148833
            },
            {
                "x": 1325.442695269829,
                "y": 1011.9296996092545
            },
            {
                "x": 1325.442695269829,
                "y": 1046.5829733208975
            },
            {
                "x": 1311.828909168826,
                "y": 1062.6719932584467
            },
            {
                "x": 1288.3141877216394,
                "y": 1076.28577935945
            },
            {
                "x": 1269.7499339475444,
                "y": 1109.7014361528204
            },
            {
                "x": 1257.373764764814,
                "y": 1154.2556452106476
            },
            {
                "x": 1225.1957248897158,
                "y": 1181.4832174126534
            },
            {
                "x": 1178.1662819953424,
                "y": 1196.3346204319294
            },
            {
                "x": 1128.6616052644238,
                "y": 1182.720834330926
            },
            {
                "x": 1087.8202469614157,
                "y": 1166.6318143933765
            },
            {
                "x": 1061.8302916776827,
                "y": 1123.3152222538217
            },
            {
                "x": 1058.1174409228636,
                "y": 1076.285779359449
            },
            {
                "x": 1068.0183762690478,
                "y": 1040.3948887295323
            },
            {
                "x": 1056.8798240045905,
                "y": 1005.7416150178898
            },
            {
                "x": 1044.5036548218602,
                "y": 980.9892766524314
            },
            {
                "x": 1049.4541224949523,
                "y": 933.95983375806
            },
            {
                "x": 1055.6422070863173,
                "y": 863.4156694165026
            },
            {
                "x": 1044.5036548218602,
                "y": 764.4063159546674
            },
            {
                "x": 1035.840336393949,
                "y": 660.4464948197408
            },
            {
                "x": 1008.6127641919448,
                "y": 539.1600368289933
            },
            {
                "x": 988.8108934995852,
                "y": 445.10115104024936
            },
            {
                "x": 966.5337889706722,
                "y": 355.99273292459765
            },
            {
                "x": 993.7613611726762,
                "y": 302.7752054388614
            },
            {
                "x": 1033.3651025574102,
                "y": 289.1614193378593
            },
            {
                "x": 1072.9688439421452,
                "y": 304.0128223571344
            },
            {
                "x": 1097.721182307605,
                "y": 334.9532453139576
            },
            {
                "x": 1108.8597345720623,
                "y": 393.1212404727856
            },
            {
                "x": 1134.8496898557942,
                "y": 458.71493714125126
            },
            {
                "x": 1176.9286650770748,
                "y": 529.2591014828087
            },
            {
                "x": 1194.2553019328936,
                "y": 562.6747582761784
            },
            {
                "x": 1204.156237279078,
                "y": 603.516116579185
            }
        ]
    },
    {
        "type": 6,
        "label": "13",
        "state": 0,
        "marked": false,
        "labels": "Segmentacao",
        "dente": -1,
        "pts": [
            {
                "x": 1339.0564813708268,
                "y": 297.82473776576944
            },
            {
                "x": 1384.8483073469267,
                "y": 359.7055836794161
            },
            {
                "x": 1431.8777502412995,
                "y": 445.1011510402487
            },
            {
                "x": 1466.531023952944,
                "y": 529.2591014828081
            },
            {
                "x": 1487.5705115635851,
                "y": 603.5161165791842
            },
            {
                "x": 1528.411869866588,
                "y": 688.9116839400181
            },
            {
                "x": 1554.4018251503203,
                "y": 737.1787437526622
            },
            {
                "x": 1582.8670142705992,
                "y": 778.0201020556688
            },
            {
                "x": 1602.6688849629675,
                "y": 813.9109926855836
            },
            {
                "x": 1610.0945864726054,
                "y": 852.2771171520446
            },
            {
                "x": 1610.0945864726054,
                "y": 933.9598337580584
            },
            {
                "x": 1603.9065018812357,
                "y": 1008.2168488544368
            },
            {
                "x": 1584.1046311888676,
                "y": 1065.1472270949935
            },
            {
                "x": 1550.6889743954976,
                "y": 1122.07760533555
            },
            {
                "x": 1504.8971484193985,
                "y": 1165.3941974751046
            },
            {
                "x": 1470.2438747077551,
                "y": 1164.1565805568316
            },
            {
                "x": 1434.3529840778383,
                "y": 1134.4537745182797
            },
            {
                "x": 1410.8382626306516,
                "y": 1099.800500806636
            },
            {
                "x": 1372.47213816419,
                "y": 1070.097694768085
            },
            {
                "x": 1344.0069490439116,
                "y": 1025.5434857102584
            },
            {
                "x": 1324.205078351544,
                "y": 966.1378736331576
            },
            {
                "x": 1308.1160584140023,
                "y": 894.3560923733272
            },
            {
                "x": 1296.9775061495452,
                "y": 815.1486096038594
            },
            {
                "x": 1280.888486211996,
                "y": 758.2182313633044
            },
            {
                "x": 1258.6113816830823,
                "y": 701.2878531227492
            },
            {
                "x": 1241.284744827264,
                "y": 618.3675195984607
            },
            {
                "x": 1225.1957248897147,
                "y": 545.3481214203573
            },
            {
                "x": 1191.7800680963467,
                "y": 471.0911063239811
            },
            {
                "x": 1145.988242120248,
                "y": 388.1707727996941
            },
            {
                "x": 1117.523052999969,
                "y": 310.20090694849904
            },
            {
                "x": 1094.549788954529,
                "y": 228.67289245726923
            },
            {
                "x": 1080.9360028535257,
                "y": 165.55442962534926
            },
            {
                "x": 1099.5002566276207,
                "y": 122.23783748579636
            },
            {
                "x": 1145.2920826037212,
                "y": 106.76762600738438
            },
            {
                "x": 1187.3710578250018,
                "y": 132.75758129111614
            },
            {
                "x": 1220.7867146183721,
                "y": 169.88608883930436
            },
            {
                "x": 1272.7666251858366,
                "y": 226.81646707985954
            },
            {
                "x": 1319.7960680802114,
                "y": 275.0835268925039
            },
            {
                "x": 1344.5484064456703,
                "y": 304.78633293105423
            }
        ]
    }
]