[
    {
        "type": 6,
        "label": "12",
        "state": 0,
        "marked": false,
        "labels": "Segmentacao",
        "dente": -1,
        "pts": [
            {
                "x": 155.8376286431026,
                "y": 1238.5779848759817
            },
            {
                "x": 67.58140834870275,
                "y": 1218.965491477226
            },
            {
                "x": 28.356421551191733,
                "y": 1176.4717557799218
            },
            {
                "x": 34.89391935077691,
                "y": 1035.9155530888388
            },
            {
                "x": 100.26889734662862,
                "y": 748.2656499070908
            },
            {
                "x": 198.33136434040634,
                "y": 427.92825772741736
            },
            {
                "x": 263.70634233625816,
                "y": 287.3720550363361
            },
            {
                "x": 312.7375758331471,
                "y": 300.4470506355064
            },
            {
                "x": 332.35006923190224,
                "y": 499.84073352285657
            },
            {
                "x": 316.00632473293956,
                "y": 758.0718966064712
            },
            {
                "x": 286.58758463480655,
                "y": 970.5405750929905
            },
            {
                "x": 260.437593436466,
                "y": 1098.021782184902
            },
            {
                "x": 234.2876022381252,
                "y": 1225.5029892768127
            },
            {
                "x": 155.57091900491972,
                "y": 1238.5097516343906
            }
        ]
    },
    {
        "type": 6,
        "label": "11",
        "state": 0,
        "marked": false,
        "labels": "Segmentacao",
        "dente": -1,
        "pts": [
            {
                "x": 433.6812851254726,
                "y": 1339.909200769552
            },
            {
                "x": 325.8125714323172,
                "y": 1339.909200769552
            },
            {
                "x": 263.70634233625816,
                "y": 1297.4154650722478
            },
            {
                "x": 257.168844536673,
                "y": 1209.1592447778469
            },
            {
                "x": 276.7813379354285,
                "y": 1009.765561890499
            },
            {
                "x": 302.93132913376917,
                "y": 960.7343283936098
            },
            {
                "x": 345.4250648310727,
                "y": 643.6656851137283
            },
            {
                "x": 397.725047227754,
                "y": 369.09077753115326
            },
            {
                "x": 450.0250296244353,
                "y": 336.4032885332275
            },
            {
                "x": 495.7875142215315,
                "y": 444.2720022263824
            },
            {
                "x": 541.5499988186278,
                "y": 728.6531565083377
            },
            {
                "x": 557.8937433175909,
                "y": 960.7343283936118
            },
            {
                "x": 570.9687389167614,
                "y": 1068.603042086768
            },
            {
                "x": 574.2374878165538,
                "y": 1238.577984875983
            },
            {
                "x": 548.0874966182128,
                "y": 1323.5654562705906
            },
            {
                "x": 431.3111254225001,
                "y": 1339.9743223470516
            }
        ]
    },
    {
        "type": 6,
        "label": "21",
        "state": 0,
        "marked": false,
        "labels": "Segmentacao",
        "dente": -1,
        "pts": [
            {
                "x": 927.2623689941533,
                "y": 1271.2654738739075
            },
            {
                "x": 806.3186597018275,
                "y": 1323.5654562705893
            },
            {
                "x": 713.8039753886421,
                "y": 1323.9821900802506
            },
            {
                "x": 669.0312059105379,
                "y": 1267.9967249741146
            },
            {
                "x": 659.22495921116,
                "y": 1111.0967777840694
            },
            {
                "x": 665.7624570107453,
                "y": 993.4218173915355
            },
            {
                "x": 652.6874614115748,
                "y": 859.4031125000394
            },
            {
                "x": 619.9999724136485,
                "y": 653.4719318131059
            },
            {
                "x": 639.6124658124043,
                "y": 441.00325332658775
            },
            {
                "x": 688.6436993092946,
                "y": 264.49081273779063
            },
            {
                "x": 737.6749328061835,
                "y": 280.8345572367534
            },
            {
                "x": 773.6311707039018,
                "y": 405.0470154288717
            },
            {
                "x": 855.3498931987165,
                "y": 640.3969362139381
            },
            {
                "x": 953.4123601924937,
                "y": 941.1218349948564
            },
            {
                "x": 992.637346990005,
                "y": 1156.8592623811678
            },
            {
                "x": 982.8311002906271,
                "y": 1228.7717381766045
            },
            {
                "x": 925.7907984880012,
                "y": 1272.4505537253947
            }
        ]
    },
    {
        "type": 6,
        "label": "22",
        "state": 0,
        "marked": false,
        "labels": "Segmentacao",
        "dente": -1,
        "pts": [
            {
                "x": 1165.8810386790121,
                "y": 1130.7092711828263
            },
            {
                "x": 1145.79607739164,
                "y": 1152.1130615162904
            },
            {
                "x": 1094.2189586856005,
                "y": 1166.6655090805455
            },
            {
                "x": 1030.7621759596507,
                "y": 1138.7559455312949
            },
            {
                "x": 976.2936024910398,
                "y": 967.2718261931955
            },
            {
                "x": 914.1873733949802,
                "y": 748.2656499070921
            },
            {
                "x": 842.2748975995429,
                "y": 441.00325332658866
            },
            {
                "x": 832.468650900165,
                "y": 267.75956163758156
            },
            {
                "x": 878.2311354972646,
                "y": 176.23459244339057
            },
            {
                "x": 910.9186244951904,
                "y": 235.07207263965725
            },
            {
                "x": 1012.2498403887607,
                "y": 450.809500025968
            },
            {
                "x": 1136.4622985808792,
                "y": 725.3844076085456
            },
            {
                "x": 1182.2247831779757,
                "y": 892.0906014979681
            },
            {
                "x": 1178.956034278183,
                "y": 1062.0655442871832
            },
            {
                "x": 1159.3435408794269,
                "y": 1140.5155178822047
            }
        ]
    }
]